mkposters
