Metadata-Version: 2.1
Name: mkposters
Version: 0.0.2
Summary: Make posters from Markdown files.
Home-page: https://github.com/patrick-kidger/mkposters
Author: Patrick Kidger
Author-email: contact@kidger.site
Maintainer: Patrick Kidger
Maintainer-email: contact@kidger.site
License: Apache-2.0
Platform: UNKNOWN
Classifier: Development Status :: 3 - Alpha
Classifier: Intended Audience :: Developers
Classifier: Intended Audience :: Information Technology
Classifier: Intended Audience :: Science/Research
Classifier: License :: OSI Approved :: Apache Software License
Classifier: Natural Language :: English
Classifier: Programming Language :: Python :: 3
Requires-Python: ~=3.7
